pymetagen/__init__.py
pymetagen/_typing.py
pymetagen/_version.py
pymetagen/app.py
pymetagen/dataloader.py
pymetagen/datatypes.py
pymetagen/exceptions.py
pymetagen/metagen.py
pymetagen/py.typed
pymetagen/utils.py
pymetagen-0.4.1.dist-info/licenses/LICENSE
pymetagen-0.4.1.dist-info/METADATA
pymetagen-0.4.1.dist-info/WHEEL
pymetagen-0.4.1.dist-info/entry_points.txt
pymetagen-0.4.1.dist-info/top_level.txt
pymetagen-0.4.1.dist-info/RECORD
