Metadata-Version: 2.4
Name: pymetagen
Version: 0.4.1
Summary: Metadata generator using polars as backend.
Author: Victor Diaz @vadrienzo, William Arnott @w-arnott
License-Expression: MIT
Project-URL: Homepage, https://github.com/itsbigspark/pymetagen
Project-URL: Issues, https://github.com/itsbigspark/pymetagen/issues
Requires-Python: <4.0,>=3.9
License-File: LICENSE
Requires-Dist: pyarrow>=15.0.0
Requires-Dist: pandas>=1.3.5
Requires-Dist: polars<1.28.0,>=1.0.0
Requires-Dist: openpyxl>=3.1.4
Requires-Dist: click>=8.1.7
Requires-Dist: xlsxwriter>=3.2.0
Provides-Extra: xlsx
Requires-Dist: xlsxwriter; extra == "xlsx"
Dynamic: license-file
